{
	"class" : {
		 },
	"instance" : {
		"==" : "SebastianSastre 3/4/2014 14:15:40",
		"defaultLabelForInspector" : "SebastianSastre 3/4/2014 14:15:40",
		"demandLoader" : "SebastianSastre 3/4/2014 14:15:40",
		"doesNotUnderstand:" : "SebastianSastre 3/4/2014 14:15:40",
		"halt" : "SebastianSastre 3/4/2014 14:15:40",
		"inspect" : "SebastianSastre 3/4/2014 14:15:40",
		"inspectorClass" : "SebastianSastre 3/4/2014 14:15:40",
		"isIdenticalTo:" : "SebastianSastre 3/4/2014 14:15:40",
		"isImmediate" : "SebastianSastre 3/4/2014 14:15:40",
		"isMorph" : "SebastianSastre 3/4/2014 14:15:40",
		"isNil" : "SebastianSastre 3/4/2014 14:15:40",
		"isODBPersistent" : "SebastianSastre 3/4/2014 14:15:40",
		"isODBReference" : "SebastianSastre 3/4/2014 14:15:40",
		"makePersistent" : "SebastianSastre 3/4/2014 14:15:40",
		"markDirty" : "SebastianSastre 3/4/2014 14:15:40",
		"notNil" : "SebastianSastre 3/4/2014 14:15:40",
		"odbGetOID" : "SebastianSastre 3/4/2014 14:15:40",
		"odbGetTransaction" : "SebastianSastre 3/4/2014 14:15:40",
		"odbNotLoaded" : "SebastianSastre 3/4/2014 14:15:40",
		"odbObjectID" : "SebastianSastre 3/4/2014 14:15:40",
		"odbResolve" : "SebastianSastre 3/4/2014 14:15:40",
		"odbSerialize:" : "SebastianSastre 3/4/2014 14:15:40",
		"odbSetLoader:" : "SebastianSastre 3/4/2014 14:15:40",
		"odbSetTransactionObject:" : "SebastianSastre 3/4/2014 14:15:40",
		"odbTransaction" : "SebastianSastre 3/4/2014 14:15:40",
		"odbTransactionObject" : "SebastianSastre 3/4/2014 14:15:40" } }
